[
  {
    "message_id": "<177435771478.81121.14256327316446596627.b4-ty@b4>",
    "title": "rust: regulator: do not assume that regulator_get() returns non-null",
    "subject": "Re: [PATCH] rust: regulator: do not assume that regulator_get() returns non-null",
    "classification": "rust_memory_safety_bug",
    "confidence": "medium",
    "summary": "The message points to a Rust memory-safety or nullness bug.",
    "evidence": "Subject/body signals include assume that, do not assume, non-null, returns non-null.",
    "published_at": "2026-03-24T13:08:34+00:00",
    "list_name": "rust-for-linux.vger.kernel.org",
    "author_name": "Mark Brown",
    "author_email": "broonie@kernel.org",
    "archive_url": null,
    "report_path": "docs/2026-03-24-rust-regulator-do-not-assume-that-regulator-get-returns-non-null.md"
  },
  {
    "message_id": "<20260320233645.950190-3-lyude@redhat.com>",
    "title": "rust/drm: Introduce DeviceContext",
    "subject": "[PATCH v6 2/5] rust/drm: Introduce DeviceContext",
    "classification": "rust_unsafe_bug",
    "confidence": "medium",
    "summary": "The message points to a Rust unsafe/soundness bug.",
    "evidence": "Subject/body signals include invariant, lifetime, non-null, nonnull, ownership, ub.",
    "published_at": "2026-03-20T23:34:27+00:00",
    "list_name": "nouveau.lists.freedesktop.org",
    "author_name": "Lyude Paul",
    "author_email": "lyude@redhat.com",
    "archive_url": null,
    "report_path": "docs/2026-03-20-patch-v6-2-5-rust-drm-introduce-devicecontext.md"
  },
  {
    "message_id": "<177398509444.378491.1876506915954121331@a3b018990fe9>",
    "title": "Rust GPU buddy allocator bindings (rev3)",
    "subject": "✓ Xe.CI.BAT: success for Rust GPU buddy allocator bindings (rev3)",
    "classification": "rust_logic_bug",
    "confidence": "medium",
    "summary": "The message describes a Rust logic or state-management bug.",
    "evidence": "Subject/body signals include bug, issue, race, regression.",
    "published_at": "2026-03-20T05:38:14+00:00",
    "list_name": "intel-xe.lists.freedesktop.org",
    "author_name": "Patchwork",
    "author_email": "patchwork@emeril.freedesktop.org",
    "archive_url": null,
    "report_path": "docs/2026-03-20-xe-ci-bat-success-for-rust-gpu-buddy-allocator-bindings-rev3.md"
  },
  {
    "message_id": "<177395813805.377450.11487247458474282015@a3b018990fe9>",
    "title": "rust: interop: Add list module for C linked list interface (rev4)",
    "subject": "✓ i915.CI.BAT: success for rust: interop: Add list module for C linked list interface (rev4)",
    "classification": "rust_logic_bug",
    "confidence": "medium",
    "summary": "The message describes a Rust logic or state-management bug.",
    "evidence": "Subject/body signals include bug, issue, race, regression.",
    "published_at": "2026-03-19T22:08:58+00:00",
    "list_name": "intel-gfx.lists.freedesktop.org",
    "author_name": "Patchwork",
    "author_email": "patchwork@emeril.freedesktop.org",
    "archive_url": null,
    "report_path": "docs/2026-03-19-i915-ci-bat-success-for-rust-interop-add-list-module-for-c-linked-list-interface-rev4.md"
  },
  {
    "message_id": "<20260319121653.2975748-4-gary@kernel.org>",
    "title": "rust: rework `build_assert!` documentation",
    "subject": "[PATCH v3 3/4] rust: rework `build_assert!` documentation",
    "classification": "rust_logic_bug",
    "confidence": "medium",
    "summary": "The message describes a Rust logic or state-management bug.",
    "evidence": "Subject/body signals include bug, issue, panic.",
    "published_at": "2026-03-19T12:16:47+00:00",
    "list_name": "rust-for-linux.vger.kernel.org",
    "author_name": "Gary Guo",
    "author_email": "gary@kernel.org",
    "archive_url": null,
    "report_path": "docs/2026-03-19-patch-v3-3-4-rust-rework-build-assert-documentation.md"
  },
  {
    "message_id": "<DH6QPWOTC3LG.F0RS2U7GDJDW@nvidia.com>",
    "title": "rust: interop: Add list module for C linked list interface",
    "subject": "Re: [PATCH v13 1/1] rust: interop: Add list module for C linked list interface",
    "classification": "rust_unsafe_bug",
    "confidence": "medium",
    "summary": "The message points to a Rust unsafe/soundness bug.",
    "evidence": "Subject/body signals include unsafe.",
    "published_at": "2026-03-19T11:59:42+00:00",
    "list_name": "rust-for-linux.vger.kernel.org",
    "author_name": "Alexandre Courbot",
    "author_email": "acourbot@nvidia.com",
    "archive_url": null,
    "report_path": "docs/2026-03-19-re-patch-v13-1-1-rust-interop-add-list-module-for-c-linked-list-interface.md"
  },
  {
    "message_id": "<20260319101153.169c7f36@fedora>",
    "title": "drm/dep: Add DRM dependency queue layer",
    "subject": "Re: [RFC PATCH 02/12] drm/dep: Add DRM dependency queue layer",
    "classification": "rust_unsafe_bug",
    "confidence": "medium",
    "summary": "The message points to a Rust unsafe/soundness bug.",
    "evidence": "Subject/body signals include assume that, contract, dangling, invariant, lifetime, non-null.",
    "published_at": "2026-03-19T09:11:53+00:00",
    "list_name": "linux-kernel.vger.kernel.org",
    "author_name": "Boris Brezillon",
    "author_email": "boris.brezillon@collabora.com",
    "archive_url": null,
    "report_path": "docs/2026-03-19-re-rfc-patch-02-12-drm-dep-add-drm-dependency-queue-layer.md"
  }
]